django_simple_task/__init__.py
django_simple_task/apps.py
django_simple_task/middleware.py
django_simple_task/task.py
django_simple_task/worker.py
django_simple_task-0.1.2.dist-info/LICENSE
django_simple_task-0.1.2.dist-info/WHEEL
django_simple_task-0.1.2.dist-info/METADATA
django_simple_task-0.1.2.dist-info/RECORD
