Metadata-Version: 2.1
Name: django-simple-task
Version: 0.1.2
Summary: Task runner for Django 3 without requiring other services
Home-page: https://github.com/ericls/django-simple-task
License: MIT
Author: Shen Li
Author-email: dustet@gmail.com
Requires-Python: >=3.7,<4
Classifier: License :: OSI Approved :: MIT License
Classifier: Programming Language :: Python :: 3
Classifier: Programming Language :: Python :: 3.7
Classifier: Programming Language :: Python :: 3.8
Requires-Dist: asgiref (>=3.2.3,<4.0.0)
Project-URL: Repository, https://github.com/ericls/django-simple-task
